madgadget/FridaGadget.py
madgadget/FridaGithub.py
madgadget/FridaScript.py
madgadget/GadgetManager.py
madgadget/__init__.py
madgadget/exceptions.py
madgadget/version.py
madgadget/android/APKEditor.py
madgadget/android/AndroidPatcher.py
madgadget/android/Apktool.py
madgadget/android/Zipalign.py
madgadget/android/__init__.py
madgadget/commands/__init__.py
madgadget/commands/inject.py
madgadget/commands/main.py
madgadget/commands/pull.py
madgadget-0.0.3.dist-info/entry_points.txt
madgadget-0.0.3.dist-info/LICENSE
madgadget-0.0.3.dist-info/WHEEL
madgadget-0.0.3.dist-info/METADATA
madgadget-0.0.3.dist-info/RECORD
