Metadata-Version: 2.1
Name: madgadget
Version: 0.0.3
Summary: madgadget
Author-email: Jacopo antipatico Scannella <code@bootkit.dev>
Classifier: Development Status :: 4 - Beta
Classifier: Intended Audience :: Developers
Classifier: License :: OSI Approved :: GNU General Public License v3 or later (GPLv3+)
Classifier: Operating System :: OS Independent
Classifier: Programming Language :: Python
Classifier: Programming Language :: Python :: 3
Classifier: Programming Language :: Python :: 3.11
Requires-Dist: lief ~= 0.13.2
Requires-Dist: requests ~= 2.31.0
Requires-Dist: semver ~= 3.0.2
Requires-Dist: pure-python-adb ~= 0.3.0.dev0
Project-URL: Github, https://github.com/antipatico/madgadget
Project-URL: Home, https://github.com/antipatico/madgadget
Project-URL: Issues, https://github.com/antipatico/madgadget/issues
